VoucherVision.py
client.py
list_prompts.py
url_name_parser.py
vouchervision_go_client-0.1.42.dist-info/licenses/LICENSE
vouchervision_go_client-0.1.42.dist-info/METADATA
vouchervision_go_client-0.1.42.dist-info/WHEEL
vouchervision_go_client-0.1.42.dist-info/entry_points.txt
vouchervision_go_client-0.1.42.dist-info/top_level.txt
vouchervision_go_client-0.1.42.dist-info/RECORD
