Metadata-Version: 2.4
Name: vouchervision-go-client
Version: 0.1.42
Summary: Client for VoucherVisionGO API
Home-page: https://github.com/Gene-Weaver/VoucherVisionGO-client
Author: Will
Author-email: willwe@umich.edu
Project-URL: Bug Tracker, https://github.com/Gene-Weaver/VoucherVisionGO/issues
Classifier: Programming Language :: Python :: 3
Classifier: License :: OSI Approved :: GNU General Public License v3 (GPLv3)
Classifier: Operating System :: OS Independent
Requires-Python: >=3.10
License-File: LICENSE
Requires-Dist: requests
Requires-Dist: requests-toolbelt
Requires-Dist: termcolor
Requires-Dist: tabulate
Requires-Dist: tqdm
Requires-Dist: pyyaml
Requires-Dist: pandas
Requires-Dist: openpyxl
Provides-Extra: analytics
Requires-Dist: pandas; extra == "analytics"
Provides-Extra: full
Requires-Dist: pandas; extra == "full"
Dynamic: author
Dynamic: author-email
Dynamic: classifier
Dynamic: description
Dynamic: description-content-type
Dynamic: home-page
Dynamic: license-file
Dynamic: project-url
Dynamic: provides-extra
Dynamic: requires-dist
Dynamic: requires-python
Dynamic: summary
